lh3/__init__.py
lh3/api.py
lh3api-0.2.0.dist-info/METADATA
lh3api-0.2.0.dist-info/WHEEL
lh3api-0.2.0.dist-info/top_level.txt
lh3api-0.2.0.dist-info/RECORD
