Metadata-Version: 2.1
Name: lh3api
Version: 0.2.0
Summary: Utilities for easily working with the LibraryH3lp APIs.
Home-page: https://gitlab.com/libraryh3lp/libraryh3lp-sdk-python
Author: Nub Games, Inc.
Author-email: support@libraryh3lp.com
License: MIT
Keywords: libraryh3lp api sdk
Platform: UNKNOWN
Classifier: Development Status :: 4 - Beta
Classifier: Intended Audience :: Developers
Classifier: License :: OSI Approved :: MIT License
Classifier: Topic :: Software Development :: Libraries
Classifier: Programming Language :: Python :: 2
Classifier: Programming Language :: Python :: 2.7
Classifier: Programming Language :: Python :: 3
Classifier: Programming Language :: Python :: 3.5
Requires-Dist: future
Requires-Dist: requests
